pyphotonfile/__init__.py
pyphotonfile/newfile.photon
pyphotonfile/photonfile.py
pyphotonfile/data/newfile.photon
pyphotonfile-0.1.1.dist-info/LICENSE
pyphotonfile-0.1.1.dist-info/METADATA
pyphotonfile-0.1.1.dist-info/WHEEL
pyphotonfile-0.1.1.dist-info/top_level.txt
pyphotonfile-0.1.1.dist-info/RECORD
