Metadata-Version: 2.1
Name: pyphotonfile
Version: 0.1.1
Summary: Library for reading and writing files for the Anycubic Photon 3D-Printer
Home-page: https://github.com/fookatchu/pyphotonfile
Author: Heiko Westermann
Author-email: heiko+pyphotonfile@orgizm.net
License: UNKNOWN
Platform: UNKNOWN
Classifier: Programming Language :: Python :: 3
Classifier: License :: OSI Approved :: GNU General Public License v3 or later (GPLv3+)
Classifier: Operating System :: OS Independent
Classifier: Development Status :: 4 - Beta
Requires-Dist: numpy
Requires-Dist: Pillow
